cell_imaging/__init__.py
tests/__init__.py
cell_imaging-1.3.2.dist-info/LICENSE
cell_imaging-1.3.2.dist-info/METADATA
cell_imaging-1.3.2.dist-info/WHEEL
cell_imaging-1.3.2.dist-info/top_level.txt
cell_imaging-1.3.2.dist-info/RECORD
