Metadata-Version: 2.1
Name: cell-imaging
Version: 1.3.2
Summary: UNKNOWN
Home-page: https://github.com/lionben89/BGU_cell_imaging
Author: Lion Ben Nedava
Author-email: lionben89@gmail.com
License: MIT
Keywords: cell_imaging
Platform: UNKNOWN
Requires-Python: >=3.6
Requires-Dist: matplotlib
Requires-Dist: numpy
Requires-Dist: tifffile
Requires-Dist: scikit-image (>=0.15.0)
Requires-Dist: aicsimageio (==3.0.7)
Requires-Dist: quilt3
Requires-Dist: bumpversion
Requires-Dist: twine
Requires-Dist: setuptools (>=42)
Requires-Dist: wheel
Requires-Dist: pandas
Requires-Dist: multipledispatch
